diffwhisperer/__init__.py
diffwhisperer/analyzer.py
diffwhisperer/cli.py
diffwhisperer-1.1.1.dist-info/METADATA
diffwhisperer-1.1.1.dist-info/WHEEL
diffwhisperer-1.1.1.dist-info/entry_points.txt
diffwhisperer-1.1.1.dist-info/licenses/LICENSE
diffwhisperer-1.1.1.dist-info/RECORD
