Metadata-Version: 2.4
Name: diffwhisperer
Version: 1.1.1
Summary: An AI agent for generating meaningful git commit messages using Google's Gemini AI
Project-URL: Homepage, https://github.com/MeherBhaskar/diffwhisperer
Project-URL: Documentation, https://github.com/MeherBhaskar/diffwhisperer#readme
Project-URL: Repository, https://github.com/MeherBhaskar/diffwhisperer.git
Project-URL: Issues, https://github.com/MeherBhaskar/diffwhisperer/issues
Author: Meher Bhaskar
License: MIT
License-File: LICENSE
Keywords: ai,cli,commit,conventional-commits,gemini,git
Classifier: Development Status :: 5 - Production/Stable
Classifier: Environment :: Console
Classifier: Intended Audience :: Developers
Classifier: License :: OSI Approved :: MIT License
Classifier: Programming Language :: Python :: 3
Classifier: Programming Language :: Python :: 3.9
Classifier: Programming Language :: Python :: 3.10
Classifier: Programming Language :: Python :: 3.11
Classifier: Programming Language :: Python :: 3.12
Classifier: Topic :: Software Development :: Libraries :: Python Modules
Classifier: Topic :: Software Development :: Version Control :: Git
Requires-Python: >=3.9
Requires-Dist: click>=8.0.0
Requires-Dist: gitpython>=3.1.44
Requires-Dist: google-generativeai>=0.3.0
